ix/__init__.py
ix-0.0.6.dist-info/licenses/LICENSE
ix-0.0.6.dist-info/METADATA
ix-0.0.6.dist-info/WHEEL
ix-0.0.6.dist-info/top_level.txt
ix-0.0.6.dist-info/RECORD
