Metadata-Version: 2.4
Name: ix
Version: 0.0.6
Summary: Audio Utils
Home-page: https://github.com/cavart/ix
Author: Thor Whalen
License: apache-2.0
Platform: any
License-File: LICENSE
Dynamic: license-file
